examples/__init__.py
examples/direct_evr_test.py
examples/test_domain_resolver.py
examples/test_url_resolution.py
examples/app_with_browser/__init__.py
examples/app_with_browser/app.py
examples/app_with_browser/mail_app.py
examples/app_with_browser/server.py
examples/evr_browser/__init__.py
examples/evr_browser/app.py
examples/ipfs_browser/__init__.py
examples/ipfs_browser/app.py
examples/simple_browser/__init__.py
examples/simple_browser/app.py
mantipy_gui/__init__.py
mantipy_gui/browser.py
mantipy_gui/custom_widgets.py
mantipy_gui/window.py
mantipy_gui/resolvers/__init__.py
mantipy_gui/resolvers/base.py
mantipy_gui/resolvers/resolver.py
mantipy_gui/resolvers/standard.py
mantipy_gui/themes/__init__.py
mantipy_gui/themes/material.py
mantipy_gui-0.2.0.dist-info/licenses/LICENSE
mantipy_gui-0.2.0.dist-info/METADATA
mantipy_gui-0.2.0.dist-info/WHEEL
mantipy_gui-0.2.0.dist-info/top_level.txt
mantipy_gui-0.2.0.dist-info/RECORD
