Metadata-Version: 2.4
Name: mantipy-gui
Version: 0.2.0
Summary: Modern Python GUI framework with web technology integration
Home-page: https://github.com/manticore-technologies/mantipy-gui
Author: Cymos
Author-email: cymos@manticore-tech.com
Classifier: Development Status :: 3 - Alpha
Classifier: Intended Audience :: Developers
Classifier: Programming Language :: Python :: 3
Classifier: License :: OSI Approved :: MIT License
Classifier: Operating System :: OS Independent
Requires-Python: >=3.7
License-File: LICENSE
Requires-Dist: PyQt5>=5.15.0
Requires-Dist: PyQtWebEngine>=5.15.0
Dynamic: author
Dynamic: author-email
Dynamic: classifier
Dynamic: description
Dynamic: description-content-type
Dynamic: home-page
Dynamic: license-file
Dynamic: requires-dist
Dynamic: requires-python
Dynamic: summary
